{
  "name": "guards",
  "version": "1.0.0",
  "title": "guards.js",
  "author": {
    "name": "Mike Virata-Stone",
    "email": "stonemj+jqueryplugins@gmail.com",
    "url": "http://reasonnumber.com/"
  },
  "licenses": [
    {
      "type": "MIT",
      "url": "https://raw.github.com/on-site/guards.js/master/MIT-LICENSE.txt"
    }
  ],
  "dependencies": {
    "jquery": "~1.4"
  },
  "description": "Guard your forms with class (or any other selector).",
  "keywords": ["validation"],
  "homepage": "http://guardsjs.com/",
  "docs": "http://guardsjs.com/documentation.html",
  "demo": "http://guardsjs.com/",
  "download": "http://guardsjs.com/downloads.html",
  "bugs": "https://github.com/on-site/guards.js/issues"
}
